corona/__init__.py
corona/app.py
corona/corona.py
corocorona-0.1.0.dist-info/METADATA
corocorona-0.1.0.dist-info/WHEEL
corocorona-0.1.0.dist-info/entry_points.txt
corocorona-0.1.0.dist-info/top_level.txt
corocorona-0.1.0.dist-info/RECORD
