Metadata-Version: 2.1
Name: corocorona
Version: 0.1.0
Summary: A covoid-19 in Japan
Home-page: https://github.com/sho-yoshikawa/corocorona
Author: syoshika
Author-email: syoshika@student.42tokyo.jp
Classifier: Programming Language :: Python :: 3
Classifier: License :: OSI Approved :: MIT License
Classifier: Operating System :: OS Independent
Requires-Python: >=3.9
Requires-Dist: requests
